rdp/__init__.py
rdp-0.7.dist-info/DESCRIPTION.rst
rdp-0.7.dist-info/METADATA
rdp-0.7.dist-info/RECORD
rdp-0.7.dist-info/WHEEL
rdp-0.7.dist-info/metadata.json
rdp-0.7.dist-info/top_level.txt
