Metadata-Version: 2.0
Name: rdp
Version: 0.7
Summary: Pure Python implementation of the Ramer-Douglas-Peucker algorithm
Home-page: http://github.com/fhirschmann/rdp
Author: Fabian Hirschmann
Author-email: fabian@hirschmann.email
License: MIT
Keywords: rdp ramer douglas peucker line simplification numpy
Platform: any
Classifier: Development Status :: 4 - Beta
Classifier: Intended Audience :: Developers
Classifier: License :: OSI Approved :: MIT License
Classifier: Operating System :: OS Independent
Classifier: Programming Language :: Python
Classifier: Programming Language :: Python :: 2
Classifier: Programming Language :: Python :: 2.5
Classifier: Programming Language :: Python :: 2.6
Classifier: Programming Language :: Python :: 2.7
Classifier: Programming Language :: Python :: 3
Classifier: Programming Language :: Python :: 3.2
Classifier: Programming Language :: Python :: 3.3
Classifier: Programming Language :: Python :: 3.4
Requires-Dist: numpy
